rowbotic/__init__.py
rowbotic/rowbotic.egg-info/PKG-INFO
rowbotic/rowbotic.egg-info/SOURCES.txt
rowbotic/rowbotic.egg-info/dependency_links.txt
rowbotic/rowbotic.egg-info/top_level.txt
rowbotic-0.1.dev1.dist-info/METADATA
rowbotic-0.1.dev1.dist-info/WHEEL
rowbotic-0.1.dev1.dist-info/RECORD
