Metadata-Version: 2.4
Name: rowbotic
Version: 0.1.dev1
Summary: Use LLMs to create tables from any corpus
Author: Sam Osian
Requires-Python: >=3.12
Requires-Dist: pandas>=2.3.3
